connect/__init__.py
connect/api.py
connect/client.py
connect/event.py
connect/exceptions.py
connect/responses.py
connect/security.py
connect_client-0.1.1.dist-info/DESCRIPTION.rst
connect_client-0.1.1.dist-info/METADATA
connect_client-0.1.1.dist-info/RECORD
connect_client-0.1.1.dist-info/WHEEL
connect_client-0.1.1.dist-info/metadata.json
connect_client-0.1.1.dist-info/top_level.txt
