Metadata-Version: 2.0
Name: connect-client
Version: 0.1.1
Summary: Python client for getconnect.io
Home-page: https://github.com/getconnect/connect-python
Author: getconnect.io
Author-email: hello@getconnect.io
License: MIT
Keywords: getconnect.io analytics connect
Platform: UNKNOWN
Classifier: Development Status :: 4 - Beta
Classifier: Intended Audience :: Developers
Classifier: License :: OSI Approved :: MIT License
Classifier: Programming Language :: Python :: 2.6
Classifier: Programming Language :: Python :: 2.7
Classifier: Programming Language :: Python :: 3.2
Classifier: Programming Language :: Python :: 3.3
Classifier: Programming Language :: Python :: 3.4
Requires-Dist: futures (>=3.0.3)
Requires-Dist: pycrypto (>=2.6)
Requires-Dist: requests
